imagify/__init__.py
imagify/bot.py
imagify/config.toml
imagify-1.0.7.dist-info/METADATA
imagify-1.0.7.dist-info/WHEEL
imagify-1.0.7.dist-info/top_level.txt
imagify-1.0.7.dist-info/RECORD
