Metadata-Version: 2.1
Name: imagify
Version: 1.0.7
Summary: Revolutionize your text into stunning visual art with our Python library! Convert plain text into captivating images effortlessly
Author: Muhammad Asif Ali
Requires-Dist: selenium
Requires-Dist: toml
Requires-Dist: requests
